lockbox/__init__.py
lockbox/app.py
lockbox/audit_log.py
lockbox/config.py
lockbox/generate_service_token.py
lockbox_proxy-0.1.3.dist-info/LICENSE
lockbox_proxy-0.1.3.dist-info/METADATA
lockbox_proxy-0.1.3.dist-info/WHEEL
lockbox_proxy-0.1.3.dist-info/RECORD
