Metadata-Version: 2.1
Name: lockbox-proxy
Version: 0.1.3
Summary: Lockbox is a forward proxy for making third party API calls.
Home-page: https://github.com/mkjt2/lockbox
License: MIT
Author: Jackie Tung
Author-email: jackie.tung@gmail.com
Requires-Python: >=3.10
Classifier: License :: OSI Approved :: MIT License
Classifier: Programming Language :: Python :: 3
Classifier: Programming Language :: Python :: 3.10
Classifier: Programming Language :: Python :: 3.11
Requires-Dist: flask (>=3.0.1,<4.0.0)
Requires-Dist: gunicorn (>=21.2.0,<22.0.0)
Requires-Dist: pydantic (>=2.5.3,<3.0.0)
Requires-Dist: pyjwt (>=2.8.0,<3.0.0)
Requires-Dist: requests (>=2.31.0,<3.0.0)
Requires-Dist: types-flask (>=1.1.6,<2.0.0)
Project-URL: Repository, https://github.com/mkjt2/lockbox
